cachetools/__init__.py
cachetools/func.py
cachetools/keys.py
cachetools-4.2.3.dist-info/LICENSE
cachetools-4.2.3.dist-info/METADATA
cachetools-4.2.3.dist-info/WHEEL
cachetools-4.2.3.dist-info/top_level.txt
cachetools-4.2.3.dist-info/RECORD
